nonebot_plugin_blive_danmaku/__init__.py
nonebot_plugin_blive_danmaku/app/__init__.py
nonebot_plugin_blive_danmaku/app/frontend/assets/echarts-0647520d.js
nonebot_plugin_blive_danmaku/app/frontend/assets/elementPlus-2f9ad77c.js
nonebot_plugin_blive_danmaku/app/frontend/assets/elementPlus-ce22a485.css
nonebot_plugin_blive_danmaku/app/frontend/assets/guard-1-k-823c4f26.png
nonebot_plugin_blive_danmaku/app/frontend/assets/guard-2-k-a0b7be7c.png
nonebot_plugin_blive_danmaku/app/frontend/assets/guard-3-k-3c7bacae.png
nonebot_plugin_blive_danmaku/app/frontend/assets/html2canvas-18c4afc9.js
nonebot_plugin_blive_danmaku/app/frontend/assets/index-01fd1861.css
nonebot_plugin_blive_danmaku/app/frontend/assets/index-13e4e779.js
nonebot_plugin_blive_danmaku/app/frontend/assets/index-35dc9657.js
nonebot_plugin_blive_danmaku/app/frontend/assets/index-434a6b8b.js
nonebot_plugin_blive_danmaku/app/frontend/assets/index-4f53a516.css
nonebot_plugin_blive_danmaku/app/frontend/assets/index-5034aea2.js
nonebot_plugin_blive_danmaku/app/frontend/assets/index-544d3f89.js
nonebot_plugin_blive_danmaku/app/frontend/assets/index-c6df6c50.js
nonebot_plugin_blive_danmaku/app/frontend/assets/index-cd2e8127.css
nonebot_plugin_blive_danmaku/app/frontend/assets/index-edb1e61b.js
nonebot_plugin_blive_danmaku/app/frontend/assets/lodash-742d3967.js
nonebot_plugin_blive_danmaku/app/frontend/assets/sc-8f8a299b.css
nonebot_plugin_blive_danmaku/app/frontend/assets/sc-badge-1-f98dcdbf.png
nonebot_plugin_blive_danmaku/app/frontend/assets/sc-badge-2-abaf3760.png
nonebot_plugin_blive_danmaku/app/frontend/assets/SC-bg-img-0e2aa755.png
nonebot_plugin_blive_danmaku/app/frontend/assets/sc-c94b5754.js
nonebot_plugin_blive_danmaku/app/frontend/assets/vendor-9f742c23.js
nonebot_plugin_blive_danmaku/app/frontend/assets/vendor-b57f6aba.css
nonebot_plugin_blive_danmaku/app/frontend/icon/favicon.ico
nonebot_plugin_blive_danmaku/app/frontend/index.html
nonebot_plugin_blive_danmaku/app/models.py
nonebot_plugin_blive_danmaku-0.4.1.dist-info/LICENSE
nonebot_plugin_blive_danmaku-0.4.1.dist-info/METADATA
nonebot_plugin_blive_danmaku-0.4.1.dist-info/WHEEL
nonebot_plugin_blive_danmaku-0.4.1.dist-info/RECORD
