Metadata-Version: 2.1
Name: nonebot-plugin-blive-danmaku
Version: 0.4.1
Summary: A danmaku plugin for Nonebot2
Home-page: https://github.com/zangxx66/nonebot_plugin_blive_danmaku
License: MIT
Keywords: nonebot,nonebot2,bilibili,danmaku
Author: ricardo
Author-email: thespirit@vip.qq.com
Requires-Python: >=3.10,<4.0
Classifier: License :: OSI Approved :: MIT License
Classifier: Operating System :: OS Independent
Classifier: Programming Language :: Python :: 3
Classifier: Programming Language :: Python :: 3.10
Classifier: Programming Language :: Python :: 3.11
Requires-Dist: Brotli (>=1.0.9,<2.0.0)
Requires-Dist: Jinja2 (>=3.1.2,<4.0.0)
Requires-Dist: Pillow (>=9.5.0,<10.0.0)
Requires-Dist: aiohttp (>=3.7.4,<4.0.0)
Requires-Dist: bilireq (>=0.2.11,<0.3.0)
Requires-Dist: nonebot-adapter-onebot (>=2.2.4,<3.0.0)
Requires-Dist: nonebot2[fastapi] (>=2.1.0,<3.0.0)
Requires-Dist: nonebot_plugin_apscheduler (>=0.3.0,<0.4.0)
Requires-Dist: pure-protobuf (>=3.0.0a5,<4.0.0)
Requires-Dist: tortoise-orm[asyncpg] (>=0.19.3,<0.20.0)
Project-URL: Documentation, https://github.com/zangxx66/nonebot_plugin_blive_danmaku#readme
